dnsimple/__init__.py
dnsimple/client.py
dnsimple/exceptions.py
dnsimple/extra.py
dnsimple/response.py
dnsimple/service/__init__.py
dnsimple/service/accounts.py
dnsimple/service/billing.py
dnsimple/service/certificates.py
dnsimple/service/contacts.py
dnsimple/service/dns_analytics.py
dnsimple/service/domains.py
dnsimple/service/identity.py
dnsimple/service/oauth.py
dnsimple/service/registrar.py
dnsimple/service/services.py
dnsimple/service/templates.py
dnsimple/service/tlds.py
dnsimple/service/vanity_name_servers.py
dnsimple/service/webhooks.py
dnsimple/service/zones.py
dnsimple/struct/__init__.py
dnsimple/struct/access_token.py
dnsimple/struct/account.py
dnsimple/struct/batch_change_zone_records.py
dnsimple/struct/certificate.py
dnsimple/struct/charge.py
dnsimple/struct/collaborator.py
dnsimple/struct/contact.py
dnsimple/struct/delegation_signer_record.py
dnsimple/struct/dns_analytics.py
dnsimple/struct/dnssec.py
dnsimple/struct/domain.py
dnsimple/struct/domain_check.py
dnsimple/struct/domain_premium_price.py
dnsimple/struct/domain_price.py
dnsimple/struct/domain_push.py
dnsimple/struct/domain_registration.py
dnsimple/struct/domain_renewal.py
dnsimple/struct/domain_restore.py
dnsimple/struct/domain_transfer.py
dnsimple/struct/domain_transfer_lock.py
dnsimple/struct/email_forward.py
dnsimple/struct/registrant.py
dnsimple/struct/service.py
dnsimple/struct/struct.py
dnsimple/struct/template.py
dnsimple/struct/template_record.py
dnsimple/struct/tld.py
dnsimple/struct/user.py
dnsimple/struct/vanity_name_server.py
dnsimple/struct/webhook.py
dnsimple/struct/whoami.py
dnsimple/struct/whois_privacy.py
dnsimple/struct/zone.py
dnsimple/struct/zone_distribution.py
dnsimple/struct/zone_file.py
dnsimple/struct/zone_record.py
dnsimple/token_authentication.py
dnsimple/version.py
dnsimple-6.1.0.dist-info/LICENSE.txt
dnsimple-6.1.0.dist-info/METADATA
dnsimple-6.1.0.dist-info/WHEEL
dnsimple-6.1.0.dist-info/RECORD
