Metadata-Version: 2.1
Name: dnsimple
Version: 6.1.0
Summary: DNSimple API service for python
Home-page: https://github.com/dnsimple/dnsimple-python
License: MIT
Author: DNSimple External Integrations Team
Author-email: support@dnsimple.com
Requires-Python: >=3.12,<4.0
Classifier: Intended Audience :: Developers
Classifier: License :: OSI Approved :: MIT License
Classifier: Operating System :: OS Independent
Classifier: Programming Language :: Python
Classifier: Programming Language :: Python :: 3
Requires-Dist: omitempty (>=0.1.1,<0.2.0)
Requires-Dist: requests (>=2.28.2,<3.0.0)
Project-URL: Repository, https://github.com/dnsimple/dnsimple-python
